odoo/addons/marginalized_groups_somconnexio/CHANGELOG.md
odoo/addons/marginalized_groups_somconnexio/README.rst
odoo/addons/marginalized_groups_somconnexio/__init__.py
odoo/addons/marginalized_groups_somconnexio/__manifest__.py
odoo/addons/marginalized_groups_somconnexio/data/mail_activity_type.xml
odoo/addons/marginalized_groups_somconnexio/data/res_partner_category.xml
odoo/addons/marginalized_groups_somconnexio/i18n/ca_ES.po
odoo/addons/marginalized_groups_somconnexio/i18n/es.po
odoo/addons/marginalized_groups_somconnexio/models/__init__.py
odoo/addons/marginalized_groups_somconnexio/models/crm_lead.py
odoo/addons/marginalized_groups_somconnexio/models/res_partner.py
odoo/addons/marginalized_groups_somconnexio/reports/CM_100_conditions.xml
odoo/addons/marginalized_groups_somconnexio/reports/CM_50_conditions.xml
odoo/addons/marginalized_groups_somconnexio/reports/CM_mixed_conditions.xml
odoo/addons/marginalized_groups_somconnexio/reports/crm_lead_creation_CM_email_template.xml
odoo/addons/marginalized_groups_somconnexio/tests/__init__.py
odoo/addons/marginalized_groups_somconnexio/tests/test_crm_lead.py
odoo/addons/marginalized_groups_somconnexio/tests/test_res_partner.py
odoo/addons/marginalized_groups_somconnexio/views/res_partner_view.xml
odoo12_addon_marginalized_groups_somconnexio-12.0.1.0.1.dist-info/METADATA
odoo12_addon_marginalized_groups_somconnexio-12.0.1.0.1.dist-info/WHEEL
odoo12_addon_marginalized_groups_somconnexio-12.0.1.0.1.dist-info/top_level.txt
odoo12_addon_marginalized_groups_somconnexio-12.0.1.0.1.dist-info/RECORD
